nodepulse/__init__.py
nodepulse/nodepulse.py
nodepulse-1.1.4.dist-info/LICENSE
nodepulse-1.1.4.dist-info/METADATA
nodepulse-1.1.4.dist-info/WHEEL
nodepulse-1.1.4.dist-info/top_level.txt
nodepulse-1.1.4.dist-info/RECORD
