Metadata-Version: 2.2
Name: nodepulse
Version: 1.1.4
Summary: A Python library to maintain and utilize a list of healthy nodes
Home-page: https://github.com/sentnl/nodepulse-python
Author: NodePulse
Author-email: charles@sentnl.io
Classifier: Programming Language :: Python :: 3
Classifier: License :: OSI Approved :: MIT License
Classifier: Operating System :: OS Independent
Requires-Python: >=3.7
License-File: LICENSE
Requires-Dist: requests>=2.25.0
Requires-Dist: schedule>=1.1.0
Requires-Dist: python-dotenv>=0.19.0
Dynamic: author
Dynamic: author-email
Dynamic: classifier
Dynamic: description
Dynamic: description-content-type
Dynamic: home-page
Dynamic: requires-dist
Dynamic: requires-python
Dynamic: summary
